README.md
setup.py
timekeep/__init__.py
timekeep/checks.py
timekeep/conversion.py
timekeep/decorators.py
timekeep/exceptions.py
timekeep/utility.py
timekeep.egg-info/PKG-INFO
timekeep.egg-info/SOURCES.txt
timekeep.egg-info/dependency_links.txt
timekeep.egg-info/requires.txt
timekeep.egg-info/top_level.txt