Metadata-Version: 2.1
Name: timekeep
Version: 0.2.0
Summary: Defensive timeseries analytics
Home-page: https://github.com/TTitcombe/timekeep
Author: Tom Titcombe
Author-email: t.j.titcombe@gmail.com
License: MIT
Keywords: timeseries time series analysis data science
Platform: UNKNOWN
Classifier: License :: OSI Approved :: MIT License
Classifier: Programming Language :: Python :: 3
Classifier: Topic :: Scientific/Engineering :: Information Analysis
Requires-Python: >=3.6
